kinya_tn/__init__.py
kinya_tn/text_normalization.py
kinya_tn/tokenize_and_classify.far
kinya_tn/verbalize.far
kinya_tn-0.0.1.3.1.dist-info/METADATA
kinya_tn-0.0.1.3.1.dist-info/WHEEL
kinya_tn-0.0.1.3.1.dist-info/licenses/LICENSE
kinya_tn-0.0.1.3.1.dist-info/RECORD
