Metadata-Version: 2.3
Name: kinya_tn
Version: 0.0.1.3.1
Summary: A small package that convert time, cardinal numbers, some acronyms and transliterations cases from their written form to their verbalized form. It can be used to normalize text before feeding it into a text-to-speech model.
Project-URL: Homepage, https://github.com/Digital-Umuganda/text_normalization_tts_rw/
Project-URL: Issues, https://github.com/Digital-Umuganda/text_normalization_tts_rw/issues
Author-email: DigitalUmuganda <samuel@digitalumuganda.com>
License-File: LICENSE
Classifier: License :: OSI Approved :: Apache Software License
Classifier: Operating System :: OS Independent
Classifier: Programming Language :: Python :: 3
Requires-Python: >=3.8
Requires-Dist: pynini
